mirage/__init__.py
mirage/constants.py
mirage/grism_tso_simulator.py
mirage/imaging_simulator.py
mirage/soss_simulator.py
mirage/temp_testing.py
mirage/version.py
mirage/wfss_simulator.py
mirage/apt/__init__.py
mirage/apt/apt_inputs.py
mirage/apt/read_apt_xml.py
mirage/catalogs/__init__.py
mirage/catalogs/besancon_client.py
mirage/catalogs/catalog_generator.py
mirage/catalogs/change_cat_mags.py
mirage/catalogs/create_catalog.py
mirage/catalogs/galmod_client.py
mirage/catalogs/get_catalog.py
mirage/catalogs/hdf5_catalog.py
mirage/catalogs/model_atmosphere.py
mirage/catalogs/photometry.py
mirage/catalogs/spectra_from_catalog.py
mirage/catalogs/utils.py
mirage/config/F070W_CLEAR_nircam_plus_ote_throughput_moda_sorted.txt
mirage/config/F070W_CLEAR_nircam_plus_ote_throughput_modb_sorted.txt
mirage/config/F070W_WLP8_nircam_plus_ote_throughput_moda_sorted.txt
mirage/config/F070W_WLP8_nircam_plus_ote_throughput_modb_sorted.txt
mirage/config/F070W_nircam_plus_ote_throughput_moda_sorted.txt
mirage/config/F070W_nircam_plus_ote_throughput_modb_sorted.txt
mirage/config/F090W_CLEAR_nircam_plus_ote_throughput_moda_sorted.txt
mirage/config/F090W_CLEAR_nircam_plus_ote_throughput_modb_sorted.txt
mirage/config/F090W_WLP8_nircam_plus_ote_throughput_moda_sorted.txt
mirage/config/F090W_WLP8_nircam_plus_ote_throughput_modb_sorted.txt
mirage/config/F090W_nircam_plus_ote_throughput_moda_sorted.txt
mirage/config/F090W_nircam_plus_ote_throughput_modb_sorted.txt
mirage/config/F115W_CLEAR_nircam_plus_ote_throughput_moda_sorted.txt
mirage/config/F115W_CLEAR_nircam_plus_ote_throughput_modb_sorted.txt
mirage/config/F115W_WLP8_nircam_plus_ote_throughput_moda_sorted.txt
mirage/config/F115W_WLP8_nircam_plus_ote_throughput_modb_sorted.txt
mirage/config/F115W_nircam_plus_ote_throughput_moda_sorted.txt
mirage/config/F115W_nircam_plus_ote_throughput_modb_sorted.txt
mirage/config/F140M_CLEAR_nircam_plus_ote_throughput_moda_sorted.txt
mirage/config/F140M_CLEAR_nircam_plus_ote_throughput_modb_sorted.txt
mirage-2.4.0.dist-info/LICENSE.txt
mirage-2.4.0.dist-info/METADATA
mirage-2.4.0.dist-info/WHEEL
mirage-2.4.0.dist-info/top_level.txt
mirage-2.4.0.dist-info/RECORD
