Metadata-Version: 2.1
Name: mirage
Version: 2.4.0
Summary: Create simulated JWST data
Home-page: https://github.com/spacetelescope/mirage
Author: STScI (Hilbert, Volk, Chambers, Sahlmann, Filippazzo et al.)
Author-email: hilbert@stsci.edu
License: UNKNOWN
Keywords: astronomy
Platform: UNKNOWN
Classifier: Intended Audience :: Science/Research
Classifier: License :: OSI Approved :: BSD License
Classifier: Operating System :: OS Independent
Classifier: Programming Language :: Python
Classifier: Topic :: Scientific/Engineering :: Astronomy
Classifier: Topic :: Software Development :: Libraries :: Python Modules
Requires-Dist: asdf (>=2.13.0)
Requires-Dist: astropy (>=5.1.1)
Requires-Dist: astroquery (>=0.4.6)
Requires-Dist: bokeh (==2.4.3)
Requires-Dist: batman-package
Requires-Dist: crds (>=11.16.16)
Requires-Dist: grismconf
Requires-Dist: gwcs (>=0.18.1)
Requires-Dist: h5py (>=3.7.0)
Requires-Dist: hotsoss (==0.1.7)
Requires-Dist: ipython
Requires-Dist: jupyter
Requires-Dist: jwst
Requires-Dist: jwst-backgrounds (>=1.1.2)
Requires-Dist: lxml (>=4.9.1)
Requires-Dist: matplotlib (>=3.6.2)
Requires-Dist: nircam-gsim
Requires-Dist: numpy (==1.23.4)
Requires-Dist: photutils (>=1.5.0)
Requires-Dist: pysiaf (==0.19.0)
Requires-Dist: scipy (>=1.9.3)
Requires-Dist: synphot (>=1.1.1)
Requires-Dist: webbpsf (>=1.1.0)
Requires-Dist: pyyaml (>=6.0)
Provides-Extra: docs
Requires-Dist: nbsphinx ; extra == 'docs'
Requires-Dist: sphinx ; extra == 'docs'
Requires-Dist: sphinx-automodapi ; extra == 'docs'
Requires-Dist: sphinx-rtd-theme ; extra == 'docs'
Requires-Dist: stsci-rtd-theme ; extra == 'docs'
Requires-Dist: extension-helpers ; extra == 'docs'
Provides-Extra: test
Requires-Dist: pytest ; extra == 'test'
